arepy/__init__.py
arepy/container.py
arepy/arepy_imgui/__init__.py
arepy/arepy_imgui/imgui_repository.py
arepy/asset_store/__init__.py
arepy/asset_store/asset_store.py
arepy/bundle/__init__.py
arepy/bundle/components/__init__.py
arepy/bundle/components/camera.py
arepy/bundle/components/light_3d.py
arepy/bundle/components/material_3d.py
arepy/bundle/components/mesh_3d.py
arepy/bundle/components/rigidbody.py
arepy/bundle/components/sprite.py
arepy/bundle/components/transform.py
arepy/bundle/systems/__init__.py
arepy/bundle/systems/movement_system.py
arepy/bundle/systems/render_system.py
arepy/ecs/__init__.py
arepy/ecs/builders.py
arepy/ecs/components.py
arepy/ecs/constants.py
arepy/ecs/entities.py
arepy/ecs/exceptions.py
arepy/ecs/registry.py
arepy/ecs/systems.py
arepy/ecs/threading.py
arepy/ecs/utils.py
arepy/ecs/world.py
arepy/ecs/query/__init__.py
arepy/ecs/query/exceptions.py
arepy/engine/__init__.py
arepy/engine/audio.py
arepy/engine/display.py
arepy/engine/engine.py
arepy/engine/input.py
arepy/engine/integrations/__init__.py
arepy/engine/integrations/imgui/__init__.py
arepy/engine/integrations/imgui/backend.py
arepy/engine/integrations/imgui/moderngl_renderer.py
arepy/engine/integrations/raylib/__init__.py
arepy/engine/integrations/raylib/audio/__init__.py
arepy/engine/integrations/raylib/audio/audio_device.py
arepy/engine/integrations/raylib/display/__init__.py
arepy/engine/integrations/raylib/display/display_repository.py
arepy/engine/integrations/raylib/input/__init__.py
arepy/engine/integrations/raylib/input/input_repository.py
arepy/engine/integrations/raylib/renderer/__init__.py
arepy/engine/integrations/raylib/renderer/renderer_2d.py
arepy/engine/integrations/raylib/renderer/renderer_3d.py
arepy/engine/integrations/raylib/renderer/stencil.py
arepy/engine/integrations/raylib/renderer/streaming.py
arepy/engine/renderer/__init__.py
arepy/engine/renderer/renderer_2d.py
arepy/engine/renderer/renderer_3d.py
arepy/event_manager/__init__.py
arepy-0.4.7.dist-info/licenses/LICENSE
arepy-0.4.7.dist-info/METADATA
arepy-0.4.7.dist-info/WHEEL
arepy-0.4.7.dist-info/top_level.txt
arepy-0.4.7.dist-info/RECORD
