Metadata-Version: 2.4
Name: arepy
Version: 0.4.7
Summary: An ECS python game engine with Raylib
Author-email: Abrahan Gil <scr44gr@protonmail.com>
License: MIT License
Keywords: ecs,game-engine,python-game-engine
Classifier: License :: OSI Approved :: MIT License
Classifier: Development Status :: 3 - Alpha
Classifier: Programming Language :: Python :: 3.10
Classifier: Programming Language :: Python :: 3.11
Classifier: Programming Language :: Python :: 3.12
Classifier: Programming Language :: Python :: 3.13
Classifier: Programming Language :: Python :: 3.14
Classifier: Operating System :: Microsoft :: Windows
Classifier: Operating System :: POSIX :: Linux
Classifier: Operating System :: MacOS :: MacOS X
Requires-Python: >=3.10
License-File: LICENSE
Requires-Dist: bitarray==3.8.0
Requires-Dist: raylib==5.5.0.3
Provides-Extra: imgui
Requires-Dist: imgui-bundle==1.6.0; extra == "imgui"
Requires-Dist: moderngl==5.12.0; extra == "imgui"
Provides-Extra: testing
Requires-Dist: pytest>=8.0.0; extra == "testing"
Requires-Dist: pytest-cov>=4.0.0; extra == "testing"
Requires-Dist: pytest-mock>=3.12.0; extra == "testing"
Dynamic: license-file
